{
  "annotations": {
    "changelogDate": "20241209210352"
  },
  "applications": "*",
  "dto": "mapstruct",
  "fields": [
    {
      "fieldName": "nombre",
      "fieldType": "String",
      "fieldValidateRules": ["required"]
    },
    {
      "fieldName": "ubicacion",
      "fieldType": "String",
      "fieldValidateRules": ["required"]
    },
    {
      "fieldName": "monto",
      "fieldType": "BigDecimal",
      "fieldValidateRules": ["required"]
    }
  ],
  "name": "Departamento",
  "pagination": "pagination",
  "relationships": [
    {
      "otherEntityName": "jefe",
      "relationshipName": "jefe",
      "relationshipSide": "left",
      "relationshipType": "many-to-one"
    }
  ],
  "searchEngine": "no",
  "service": "serviceClass"
}
